termify/__init__.py
termify/__main__.py
termify/__version__.py
termify/playbackMonitor.py
termify/spotifyAppController.py
termify/menus/__init__.py
termify/menus/mainMenu.py
termify/menus/playbackDeviceSelector.py
termify/menus/playlistSelectMenu.py
termify/spotifyApi/__init__.py
termify/spotifyApi/spotifyApi.py
termify/spotifyApi/spotifyAuthorizer.py
termify_py-1.2.0.dist-info/LICENSE
termify_py-1.2.0.dist-info/METADATA
termify_py-1.2.0.dist-info/WHEEL
termify_py-1.2.0.dist-info/entry_points.txt
termify_py-1.2.0.dist-info/top_level.txt
termify_py-1.2.0.dist-info/RECORD
