Metadata-Version: 2.1
Name: termify-py
Version: 1.2.0
Summary: A terminal-based Spotify controller
Home-page: https://github.com/evanlaube/termify
Author: Evan Laube
Author-email: laubeevan@gmail.com
License: GPL-3.0
License-File: LICENSE
Requires-Dist: requests
Requires-Dist: procyon-py
Requires-Dist: python-dotenv
Provides-Extra: windows
Requires-Dist: windows-curses; extra == "windows"
